LICENSE.txt
README.md
pyproject.toml
src/uphy/__init__.py
src/uphy.egg-info/PKG-INFO
src/uphy.egg-info/SOURCES.txt
src/uphy.egg-info/dependency_links.txt
src/uphy.egg-info/entry_points.txt
src/uphy.egg-info/requires.txt
src/uphy.egg-info/top_level.txt
src/uphy/cli/__init__.py
src/uphy/cli/__main__.py