Metadata-Version: 2.2
Name: uphy
Version: 0.1.0.dev2895
Author-email: RT-Labs <support@rt-labs.com>
License: Copyright rt-labs AB, Sweden.
Project-URL: RT-Labs, https://rt-labs.com
Project-URL: U-Phy, https://rt-labs.com/u-phy
Project-URL: Documentation, https://docs.rt-labs.com/u-phy
License-File: LICENSE.txt
Requires-Dist: typer>=0.12.5
Requires-Dist: uphy-device>=0.1.0.dev0
Requires-Dist: uphy-controller>=0.1.0.dev0
